rlretry/__init__.py
rlretry/auto_rate_limit.py
rlretry/rlretry.py
rlretry-0.0.11.dist-info/LICENSE
rlretry-0.0.11.dist-info/METADATA
rlretry-0.0.11.dist-info/WHEEL
rlretry-0.0.11.dist-info/top_level.txt
rlretry-0.0.11.dist-info/RECORD
