Metadata-Version: 2.1
Name: rlretry
Version: 0.0.11
Summary: A small example package
Author-email: kbb29 <kbb29@github.com>
Project-URL: Homepage, https://github.com/kbb29/rlretry
Project-URL: Bug Tracker, https://github.com/kbb29/rlretry/issues
Classifier: Programming Language :: Python :: 3
Classifier: License :: OSI Approved :: MIT License
Classifier: Operating System :: OS Independent
Requires-Python: >=3.8
License-File: LICENSE
Requires-Dist: pandas ~=2.0
Provides-Extra: dev
Requires-Dist: pytest ~=7.4.2 ; extra == 'dev'
